{
  "id": "power_threshold_exceeded",
  "title": {
    "en": "Power threshold exceeded",
    "nl": "Vermogen drempel overschreden",
    "de": "Leistungs-Schwellenwert überschritten",
    "fr": "Seuil de puissance dépassé"
  },
  "titleFormatted": {
    "en": "Power consumption exceeded [[threshold]] W",
    "nl": "Stroomverbruik overschreed [[threshold]] W",
    "de": "Leistungsaufnahme überschritt [[threshold]] W",
    "fr": "Consommation dépassée [[threshold]] W"
  },
  "hint": {
    "en": "Triggers when power consumption exceeds specified threshold (requires power monitoring support)",
    "nl": "Wordt geactiveerd wanneer stroomverbruik een drempel overschrijdt (vereist vermogen monitoring ondersteuning)",
    "de": "Wird ausgelöst, wenn die Leistungsaufnahme den angegebenen Schwellenwert überschreitet (erfordert Leistungsüberwachung)",
    "fr": "Se déclenche lorsque la consommation dépasse le seuil spécifié (nécessite la surveillance de la puissance)"
  },
  "args": [
    {
      "type": "device",
      "name": "device",
      "filter": "driver_id=intelligent-heatpump-modbus"
    },
    {
      "type": "range",
      "name": "threshold",
      "title": {
        "en": " Power threshold (W)",
        "nl": " Vermogen drempel (W)",
        "de": " Leistungs-Schwellenwert (W)",
        "fr": " Seuil de puissance (W)"
      },
      "min": 100,
      "max": 10000,
      "step": 100,
      "units": "W",
      "placeholder": {
        "en": "Power threshold in watts",
        "nl": "Vermogen drempel in watt",
        "de": "Leistungs-Schwellenwert in Watt",
        "fr": "Seuil de puissance en watts"
      }
    }
  ],
  "tokens": [
    {
      "type": "number",
      "name": "current_power",
      "title": {
        "en": "Current power consumption",
        "nl": "Huidig stroomverbruik",
        "de": "Aktuelle Leistungsaufnahme",
        "fr": "Consommation actuelle"
      },
      "example": 3500
    },
    {
      "type": "number",
      "name": "threshold_power",
      "title": {
        "en": "Threshold power",
        "nl": "Drempel vermogen",
        "de": "Schwellenwert Leistung",
        "fr": "Puissance seuil"
      },
      "example": 3000
    }
  ]
}
