{
  "id": "adlar_cop_monthly",
  "title": {
    "en": "Rolling Monthly Average COP",
    "nl": "Voortschrijdend Maandelijkse Gemiddelde COP",
    "de": "Gleitender Monatsdurchschnitt COP",
    "fr": "Moyenne mobile mensuelle COP"
  },
  "type": "number",
  "units": {
    "en": "COP",
    "nl": "COP",
    "de": "COP",
    "fr": "COP"
  },
  "min": 0,
  "max": 8,
  "step": 0.01,
  "decimals": 2,
  "getable": true,
  "setable": false,
  "uiComponent": "sensor",
  "insights": true,
  "insightsTitle": {
    "en": "Monthly Heat Pump Efficiency (COP)",
    "nl": "Maandelijkse Warmtepomp Efficiëntie (COP)",
    "de": "Monatliche Wärmepumpen Effizienz (COP)",
    "fr": "Efficacité mensuelle de la pompe à chaleur (COP)"
  },
  "icon": "/assets/cop-efficiency.svg",
  "description": {
    "en": "Monthly average COP derived from accumulated thermal output and electrical input measurements.",
    "nl": "Maandelijkse gemiddelde COP afgeleid uit opgebouwde thermische opbrengst en elektrisch verbruik.",
    "fr": "COP moyen mensuel dérivé de la chaleur produite et de l’énergie électrique consommée cumulées.",
    "de": "Monatlicher durchschnittlicher COP, abgeleitet aus kumulierter Wärmeabgabe und elektrischem Eingang."
  }
}
